daglite/__init__.py
daglite/engine.py
daglite/exceptions.py
daglite/futures.py
daglite/pipelines.py
daglite/py.typed
daglite/serialization.py
daglite/settings.py
daglite/tasks.py
daglite/backends/__init__.py
daglite/backends/base.py
daglite/backends/context.py
daglite/backends/local.py
daglite/backends/distributed/__init__.py
daglite/cache/__init__.py
daglite/cache/base.py
daglite/cache/core.py
daglite/cache/store.py
daglite/graph/__init__.py
daglite/graph/base.py
daglite/graph/builder.py
daglite/graph/nodes.py
daglite/outputs/__init__.py
daglite/outputs/base.py
daglite/outputs/store.py
daglite/plugins/__init__.py
daglite/plugins/base.py
daglite/plugins/events.py
daglite/plugins/manager.py
daglite/plugins/reporters.py
daglite/plugins/builtin/__init__.py
daglite/plugins/builtin/cache.py
daglite/plugins/builtin/logging.json
daglite/plugins/builtin/logging.py
daglite/plugins/builtin/output.py
daglite/plugins/hooks/__init__.py
daglite/plugins/hooks/markers.py
daglite/plugins/hooks/specs.py
daglite-0.7.0.dist-info/METADATA
daglite-0.7.0.dist-info/WHEEL
daglite-0.7.0.dist-info/top_level.txt
daglite-0.7.0.dist-info/RECORD
