Metadata-Version: 2.4
Name: daglite
Version: 0.7.0
Summary: Lightweight Python framework for building static DAGs with explicit bindings.
Requires-Python: >=3.10
Requires-Dist: fsspec>=2026.1.0
Requires-Dist: pluggy>=1.6.0
Requires-Dist: typing-extensions>=4.15.0
Provides-Extra: cli
Requires-Dist: daglite-cli; extra == "cli"
Provides-Extra: serialization
Requires-Dist: daglite-serialization; extra == "serialization"
Provides-Extra: rich
Requires-Dist: daglite-rich; extra == "rich"
